socialgroupdetection/__init__.py
socialgroupdetection/dictionary.py
socialgroupdetection/embeddings.py
socialgroupdetection/filtering.py
socialgroupdetection/main.py
socialgroupdetection/system_prompt.py
socialgroupdetection-0.0.1.dist-info/LICENSE
socialgroupdetection-0.0.1.dist-info/METADATA
socialgroupdetection-0.0.1.dist-info/NOTICE.txt
socialgroupdetection-0.0.1.dist-info/WHEEL
socialgroupdetection-0.0.1.dist-info/top_level.txt
socialgroupdetection-0.0.1.dist-info/RECORD
