Metadata-Version: 2.1
Name: socialgroupdetection
Version: 0.0.1
Summary: a python library to detect social groups mentioned in political texts
Home-page: https://github.com/juliandehne/socialgroupdetection
Author: Julian Dehne
License: MIT
Classifier: Intended Audience :: Developers
Classifier: License :: OSI Approved :: MIT License
Classifier: Programming Language :: Python :: 3.9
Classifier: Operating System :: OS Independent
Requires-Python: >=3.9, <3.10
License-File: LICENSE
License-File: NOTICE.txt
Requires-Dist: numpy ==1.22.3
Requires-Dist: pandas ~=1.5.3
Requires-Dist: tqdm
Requires-Dist: jupyter
Requires-Dist: scikit-learn
Requires-Dist: transformers
Requires-Dist: torch
